{
  "model_name": "lead_scoring_lgbm_v2",
  "version": "v2",
  "train_date": "2026-06-23",
  "features": [
    "hora_lead",
    "dia_semana",
    "has_vtex",
    "tiempo_pagina_s",
    "paginas_sesion",
    "uso_comparador",
    "items_carrito",
    "sesiones_72h",
    "is_prime_time",
    "is_weekend",
    "is_begin_checkout",
    "is_add_to_cart",
    "is_sin_vtex",
    "is_mobile",
    "is_paid",
    "is_wsp_inbound",
    "is_formulario",
    "tiempo_log",
    "engagement_score",
    "intent_score",
    "canal_origen",
    "device",
    "source_medium",
    "producto_visto",
    "cat_producto",
    "punto_abandono"
  ],
  "features_num": [
    "hora_lead",
    "dia_semana",
    "has_vtex",
    "tiempo_pagina_s",
    "paginas_sesion",
    "uso_comparador",
    "items_carrito",
    "sesiones_72h",
    "is_prime_time",
    "is_weekend",
    "is_begin_checkout",
    "is_add_to_cart",
    "is_sin_vtex",
    "is_mobile",
    "is_paid",
    "is_wsp_inbound",
    "is_formulario",
    "tiempo_log",
    "engagement_score",
    "intent_score"
  ],
  "features_cat": [
    "canal_origen",
    "device",
    "source_medium",
    "producto_visto",
    "cat_producto",
    "punto_abandono"
  ],
  "le_dict": {
    "canal_origen": [
      "boton_ayuda",
      "formulario_web",
      "whatsapp_inbound"
    ],
    "device": [
      "desktop",
      "mobile",
      "tablet"
    ],
    "source_medium": [
      "directo",
      "email_claro",
      "facebook_ads",
      "google_cpc",
      "google_organic",
      "whatsapp_link"
    ],
    "producto_visto": [
      "Motorola Edge",
      "Plan 100GB",
      "Plan 10GB",
      "Plan 20GB",
      "Plan 50GB",
      "Plan Hogar",
      "Samsung A55",
      "Tablet",
      "Xiaomi 14T",
      "iPhone 15",
      "sin_dato"
    ],
    "cat_producto": [
      "equipo",
      "internet_hogar",
      "plan_movil",
      "sin_dato"
    ],
    "punto_abandono": [
      "add_to_cart",
      "begin_checkout",
      "sin_sesion_vtex",
      "view_item"
    ]
  },
  "score_buckets": {
    "A": 0.75,
    "B": 0.5,
    "C": 0.3
  },
  "tier_map": {
    "A · Urgente": {
      "sla": "< 1 hora",
      "accion": "Llamada inmediata · agente senior"
    },
    "B · Alta": {
      "sla": "< 4 horas",
      "accion": "Cola prioritaria · oferta preparada"
    },
    "C · Media": {
      "sla": "< 24 horas",
      "accion": "Cola estándar · nurturing previo"
    },
    "D · Baja": {
      "sla": "Sin contacto",
      "accion": "Descarte temporal"
    }
  },
  "metrics": {
    "auc_roc": 0.7342,
    "average_prec": 0.8359,
    "ks_statistic": 0.3737,
    "precision_top20": 0.9167,
    "lift_top20": 1.4353
  },
  "shap_top10": [
    {
      "feature": "intent_score",
      "shap_mean": 0.326416338958924
    },
    {
      "feature": "engagement_score",
      "shap_mean": 0.2275141545134865
    },
    {
      "feature": "is_wsp_inbound",
      "shap_mean": 0.1869628006024184
    },
    {
      "feature": "hora_lead",
      "shap_mean": 0.14285198406648306
    },
    {
      "feature": "items_carrito",
      "shap_mean": 0.12258513298869786
    },
    {
      "feature": "tiempo_pagina_s",
      "shap_mean": 0.0908663476718849
    },
    {
      "feature": "producto_visto",
      "shap_mean": 0.07412619966105546
    },
    {
      "feature": "is_prime_time",
      "shap_mean": 0.07388017650390157
    },
    {
      "feature": "is_mobile",
      "shap_mean": 0.06677553894090044
    },
    {
      "feature": "cat_producto",
      "shap_mean": 0.0480973214349444
    }
  ],
  "best_iteration": 69,
  "arquitectura": "near_real_time · Pub/Sub → Cloud_Function → Vertex_AI_Endpoint → CRM",
  "features_eliminados_vs_v1": [
    "plan_actual_crm",
    "antigüedad_meses",
    "nps_historico",
    "visitas_30d",
    "es_reactivo"
  ],
  "nota": "CRM solo para etiqueta historica de entrenamiento. No usado en scoring RT."
}